meshmem/__init__.py
meshmem/audit.py
meshmem/clarifier.py
meshmem/cmb.py
meshmem/events.py
meshmem/layer.py
meshmem/memory_evolution.py
meshmem/svaf_api.py
meshmem/svaf_fusion.py
meshmem/vee.py
meshmem-0.1.1.dist-info/licenses/IP_NOTICE.md
meshmem-0.1.1.dist-info/licenses/LICENSE
meshmem-0.1.1.dist-info/METADATA
meshmem-0.1.1.dist-info/WHEEL
meshmem-0.1.1.dist-info/top_level.txt
meshmem-0.1.1.dist-info/RECORD
