Metadata-Version: 2.4
Name: meshmem
Version: 0.1.1
Summary: MeshMem SDK – Protocol-native, auditable, and composable cognitive memory for AI and multi-agent systems
Home-page: https://meshmem.io
Author: Hongwei Xu, Consenix Labs Ltd
Author-email: Consenix Labs Ltd <info@consenix.com>
License: # MeshMem SDK – License & Intellectual Property Notice
Project-URL: Homepage, https://meshmem.io
Project-URL: Documentation, https://docs.meshmem.io
Project-URL: Repository, https://github.com/meshmem/meshmem-sdk
Classifier: Programming Language :: Python :: 3
Classifier: Operating System :: OS Independent
Requires-Python: >=3.8
License-File: LICENSE
License-File: IP_NOTICE.md
Requires-Dist: numpy>=1.20
Dynamic: author
Dynamic: home-page
Dynamic: license-file
Dynamic: requires-python
